playwright_dompath/__init__.py
playwright_dompath/dompath_async.py
playwright_dompath/dompath_sync.py
playwright_dompath-0.0.1.dist-info/LICENSE.md
playwright_dompath-0.0.1.dist-info/METADATA
playwright_dompath-0.0.1.dist-info/WHEEL
playwright_dompath-0.0.1.dist-info/top_level.txt
playwright_dompath-0.0.1.dist-info/RECORD
