Metadata-Version: 2.1
Name: playwright-dompath
Version: 0.0.1
Summary: Retrieve xpath and css selectors from Locator objects in Playwright
Author-email: Alex Ferrari <alex@thealexferrari.com>
Project-URL: Homepage, https://github.com/alexferrari88/playwright-dompath-py
Keywords: playwright,scraper,dompath
Classifier: Intended Audience :: Developers
Classifier: License :: OSI Approved :: MIT License
Classifier: Environment :: Plugins
Classifier: Programming Language :: Python
Classifier: Programming Language :: Python :: 3
Classifier: Operating System :: OS Independent
Requires-Python: >=3.9
License-File: LICENSE.md
Requires-Dist: playwright (>=1.22.0)
Provides-Extra: dev
Requires-Dist: black ; extra == 'dev'
Requires-Dist: isort ; extra == 'dev'
Requires-Dist: pip-tools ; extra == 'dev'
Requires-Dist: pytest ; extra == 'dev'
